mac_gurl/__init__.py
mac_gurl/adapter.py
mac_gurl/gurl.py
mac_gurl-0.1.1.dist-info/licenses/LICENSE
mac_gurl-0.1.1.dist-info/METADATA
mac_gurl-0.1.1.dist-info/WHEEL
mac_gurl-0.1.1.dist-info/top_level.txt
mac_gurl-0.1.1.dist-info/RECORD
