Metadata-Version: 2.4
Name: mac-gurl
Version: 0.1.1
Summary: Add your description here
License-Expression: Apache-2.0
Project-URL: Homepage, https://github.com/toanju/mac-gurl
Project-URL: Documentation, https://github.com/toanju/mac-gurl
Project-URL: Repository, https://github.com/toanju/mac-gurl
Project-URL: Issues, https://github.com/toanju/mac-gurl/issues
Project-URL: Changelog, https://github.com/toanju/mac-gurl/blob/main/CHANGELOG.md
Requires-Python: >=3.9
License-File: LICENSE
Requires-Dist: asn1crypto>=1.5.1
Requires-Dist: pyobjc>=11.0
Requires-Dist: requests>=2.32.3
Requires-Dist: xattr>=1.1.4
Dynamic: license-file
